ovos_skill_fuster_quotes/README.md
ovos_skill_fuster_quotes/__init__.py
ovos_skill_fuster_quotes/version.py
ovos_skill_fuster_quotes/gui/all/fuster.png
ovos_skill_fuster_quotes/locale/ca/Fuster.voc
ovos_skill_fuster_quotes/locale/ca/birth.voc
ovos_skill_fuster_quotes/locale/ca/death.voc
ovos_skill_fuster_quotes/locale/ca/fuster_quotes.dialog
ovos_skill_fuster_quotes/locale/ca/fuster_quotes.intent
ovos_skill_fuster_quotes/locale/ca/live.voc
ovos_skill_fuster_quotes/locale/ca/quote.voc
ovos_skill_fuster_quotes/locale/ca/skill.json
ovos_skill_fuster_quotes/locale/ca/when.voc
ovos_skill_fuster_quotes/locale/ca/when_did_joan_fuster_die.dialog
ovos_skill_fuster_quotes/locale/ca/when_was_joan_fuster_born.dialog
ovos_skill_fuster_quotes/locale/ca/who.intent
ovos_skill_fuster_quotes/locale/ca/who_was_joan_fuster.dialog
ovos_skill_fuster_quotes/locale/en/Fuster.voc
ovos_skill_fuster_quotes/locale/en/birth.voc
ovos_skill_fuster_quotes/locale/en/death.voc
ovos_skill_fuster_quotes/locale/en/fuster_quotes.dialog
ovos_skill_fuster_quotes/locale/en/fuster_quotes.intent
ovos_skill_fuster_quotes/locale/en/live.voc
ovos_skill_fuster_quotes/locale/en/quote.voc
ovos_skill_fuster_quotes/locale/en/skill.json
ovos_skill_fuster_quotes/locale/en/when.voc
ovos_skill_fuster_quotes/locale/en/when_did_joan_fuster_die.dialog
ovos_skill_fuster_quotes/locale/en/when_was_joan_fuster_born.dialog
ovos_skill_fuster_quotes/locale/en/who_was_joan_fuster.dialog
ovos_skill_fuster_quotes/ovos_skill_fuster_quotes.egg-info/PKG-INFO
ovos_skill_fuster_quotes/ovos_skill_fuster_quotes.egg-info/SOURCES.txt
ovos_skill_fuster_quotes/ovos_skill_fuster_quotes.egg-info/dependency_links.txt
ovos_skill_fuster_quotes/ovos_skill_fuster_quotes.egg-info/entry_points.txt
ovos_skill_fuster_quotes/ovos_skill_fuster_quotes.egg-info/requires.txt
ovos_skill_fuster_quotes/ovos_skill_fuster_quotes.egg-info/top_level.txt
ovos_skill_fuster_quotes-0.0.4.dist-info/METADATA
ovos_skill_fuster_quotes-0.0.4.dist-info/WHEEL
ovos_skill_fuster_quotes-0.0.4.dist-info/entry_points.txt
ovos_skill_fuster_quotes-0.0.4.dist-info/top_level.txt
ovos_skill_fuster_quotes-0.0.4.dist-info/RECORD
