Metadata-Version: 2.1
Name: ovos-skill-fuster-quotes
Version: 0.0.4
Summary: JoanFusterQuotesSkill
Home-page: https://github.com/OpenVoiceOS/ovos-skill-fuster-quotes
Author: OpenVoiceOS
Author-email: 
License: Apache2.0
Keywords: ovos skill plugin
Requires-Dist: ovos-workshop
